setup.py
struc/__init__.py
struc.egg-info/PKG-INFO
struc.egg-info/SOURCES.txt
struc.egg-info/dependency_links.txt
struc.egg-info/top_level.txt