Metadata-Version: 1.0
Name: struc
Version: 0.2
Summary: syntax wrapper for ctypes.Structure
Home-page: http://code.google.com/p/struc
Author: invlpg
Author-email: invlpg@gmail.com
License: MIT
Platform: UNKNOWN
